{
  "employees": [
    {
      "name": "Elex",
      "phone": "0915518407",
      "address": "Quang Nam",
      "email": "alex@example.com",
      "status": false,
      "gender": "false",
      "id": 1
    },
    {
      "name": "Jenk Oz",
      "phone": "0283002890",
      "address": "LonDon",
      "email": "jenk@gmail.com",
      "status": true,
      "gender": "true",
      "id": 3
    }
  ],
  "users":[
    {
      "id":1,
      "eId":1,
      "username":"jenk",
      "password":"122abc",
      "token":"snjiwueueo92sw9283232i2okwookwoi02930293029320930kws0ksokoi20"
    }
  ]
}